physicspy-0.0.2.dist-info/DESCRIPTION.rst
physicspy-0.0.2.dist-info/METADATA
physicspy-0.0.2.dist-info/RECORD
physicspy-0.0.2.dist-info/WHEEL
physicspy-0.0.2.dist-info/metadata.json
physicspy-0.0.2.dist-info/top_level.txt
physpy/__init__.py
physpy/diff.py
